tanos/VERSION
tanos/__init__.py
tanos/calcScore.py
tanos/node.py
tanos/tree.py
tanos-0.0.1b7.dist-info/LICENSE
tanos-0.0.1b7.dist-info/METADATA
tanos-0.0.1b7.dist-info/WHEEL
tanos-0.0.1b7.dist-info/entry_points.txt
tanos-0.0.1b7.dist-info/top_level.txt
tanos-0.0.1b7.dist-info/RECORD
