Metadata-Version: 2.1
Name: tanos
Version: 0.0.1b7
Summary: TANOS: TAxon jackknife for NOdal Stability. In phylogenetic trees, calculate how resilient nodes are to the removal of taxa
Home-page: https://github.com/pickettbd/tanos
Author: Brandon Pickett
Author-email: pickettbd@byu.edu
License: UNKNOWN
Project-URL: Source, https://github.com/pickettbd/tanos
Project-URL: Bug Reports, https://github.com/pickettbd/tanos/issues
Project-URL: Buy me a soda!, http://buymeacoff.ee/pickettbd
Keywords: phylogeny,phylogenetic,taxonomy,taxa,taxon,resilience,resiliency,tree,systematics,nodal stability
Platform: UNKNOWN
Classifier: Development Status :: 4 - Beta
Classifier: Intended Audience :: Science/Research
Classifier: Topic :: Scientific/Engineering
Classifier: Topic :: Scientific/Engineering :: Bio-Informatics
Classifier: License :: OSI Approved :: MIT License
Classifier: Programming Language :: Python :: 3
Classifier: Programming Language :: Python :: 3.6
Classifier: Programming Language :: Python :: 3.7
Classifier: Programming Language :: Python :: 3.8
Classifier: Programming Language :: Python :: 3 :: Only
Classifier: Environment :: Console
Classifier: Natural Language :: English
Classifier: Operating System :: MacOS
Classifier: Operating System :: POSIX :: Linux
Requires-Python: >=3.6, <4
